noisy_graph_states/__init__.py
noisy_graph_states/noisy_graph_states.py
noisy_graph_states/version.py
noisy_graph_states/libs/__init__.py
noisy_graph_states/libs/graph.py
noisy_graph_states/libs/matrix.py
noisy_graph_states/tools/__init__.py
noisy_graph_states/tools/density_matrix.py
noisy_graph_states/tools/patterns.py
noisy_graph_states/tools/strategies_1d.py
noisy_graph_states-0.4.dist-info/licenses/LICENSE
noisy_graph_states-0.4.dist-info/METADATA
noisy_graph_states-0.4.dist-info/WHEEL
noisy_graph_states-0.4.dist-info/top_level.txt
noisy_graph_states-0.4.dist-info/RECORD
