Metadata-Version: 2.4
Name: noisy_graph_states
Version: 0.4
Summary: A tool to treat noise on graph states.
Author: Julius Wallnöfer, Maria Flors Mor-Ruiz
License: MIT License
Project-URL: homepage, https://github.com/jwallnoefer/noisy_graph_states
Keywords: quantum information,quantum information theory,graph,graph state,stabilizer state,stabilizer formalism,entanglement,multipartite entanglement
Classifier: License :: OSI Approved :: MIT License
Classifier: Programming Language :: Python :: 3
Classifier: Topic :: Scientific/Engineering :: Physics
Classifier: Intended Audience :: Science/Research
Requires-Python: >=3.8
License-File: LICENSE
Requires-Dist: numpy>=1.24.3
Requires-Dist: networkx>=2.0.1
Provides-Extra: test
Requires-Dist: pytest>=7.4.0; extra == "test"
Provides-Extra: docs
Requires-Dist: Sphinx>=6.2.1; extra == "docs"
Requires-Dist: autodocsumm>=0.2.11; extra == "docs"
Requires-Dist: recommonmark>=0.7.1; extra == "docs"
Requires-Dist: sphinx-rtd-theme>=1.2.2; extra == "docs"
Dynamic: license-file
